[
  {
    "timestamp": "2026-05-25T00:55:26.085Z",
    "totalEvents": 300,
    "pagesCollected": 10,
    "eventsInFile": 22,
    "rateLimitRemaining": 4989,
    "rateLimitReached": false,
    "rateLimitReset": "2026-05-25T01:54:54.000Z",
    "oldestEventAt": "2026-05-24T10:46:22.000Z",
    "newestEventAt": "2026-05-25T00:52:38.000Z",
    "gapSuspected": false,
    "error": null,
    "collectionPath": "./stats-data",
    "repo": "AdguardTeam/AdguardFilters"
  },
  {
    "timestamp": "2026-05-25T01:47:47.736Z",
    "totalEvents": 300,
    "pagesCollected": 10,
    "eventsInFile": 41,
    "rateLimitRemaining": 4978,
    "rateLimitReached": false,
    "rateLimitReset": "2026-05-25T01:54:54.000Z",
    "oldestEventAt": "2026-05-24T12:27:07.000Z",
    "newestEventAt": "2026-05-25T01:42:42.000Z",
    "gapSuspected": false,
    "error": null,
    "collectionPath": "./stats-data",
    "repo": "AdguardTeam/AdguardFilters"
  },
  {
    "timestamp": "2026-05-25T03:15:15.364Z",
    "totalEvents": 300,
    "pagesCollected": 10,
    "eventsInFile": 80,
    "rateLimitRemaining": 4989,
    "rateLimitReached": false,
    "rateLimitReset": "2026-05-25T04:14:48.000Z",
    "oldestEventAt": "2026-05-24T14:49:48.000Z",
    "newestEventAt": "2026-05-25T03:08:43.000Z",
    "gapSuspected": false,
    "error": null,
    "collectionPath": "./stats-data",
    "repo": "AdguardTeam/AdguardFilters"
  },
  {
    "timestamp": "2026-05-25T05:03:15.296Z",
    "totalEvents": 300,
    "pagesCollected": 10,
    "eventsInFile": 121,
    "rateLimitRemaining": 4989,
    "rateLimitReached": false,
    "rateLimitReset": "2026-05-25T06:02:46.000Z",
    "oldestEventAt": "2026-05-24T17:15:56.000Z",
    "newestEventAt": "2026-05-25T05:01:25.000Z",
    "gapSuspected": true,
    "error": null,
    "collectionPath": "./stats-data",
    "repo": "AdguardTeam/AdguardFilters"
  },
  {
    "timestamp": "2026-05-25T06:56:14.332Z",
    "totalEvents": 300,
    "pagesCollected": 10,
    "eventsInFile": 211,
    "rateLimitRemaining": 4989,
    "rateLimitReached": false,
    "rateLimitReset": "2026-05-25T07:55:44.000Z",
    "oldestEventAt": "2026-05-24T19:33:58.000Z",
    "newestEventAt": "2026-05-25T06:55:37.000Z",
    "gapSuspected": true,
    "error": null,
    "collectionPath": "./stats-data",
    "repo": "AdguardTeam/AdguardFilters"
  },
  {
    "timestamp": "2026-05-25T08:35:54.060Z",
    "totalEvents": 300,
    "pagesCollected": 10,
    "eventsInFile": 340,
    "rateLimitRemaining": 4989,
    "rateLimitReached": false,
    "rateLimitReset": "2026-05-25T09:35:23.000Z",
    "oldestEventAt": "2026-05-21T16:38:06.000Z",
    "newestEventAt": "2026-05-25T08:35:23.000Z",
    "gapSuspected": true,
    "error": null,
    "collectionPath": "./stats-data",
    "repo": "AdguardTeam/AdguardFilters"
  },
  {
    "timestamp": "2026-05-25T10:36:45.549Z",
    "totalEvents": 300,
    "pagesCollected": 10,
    "eventsInFile": 546,
    "rateLimitRemaining": 4989,
    "rateLimitReached": false,
    "rateLimitReset": "2026-05-25T11:36:17.000Z",
    "oldestEventAt": "2026-05-21T16:38:06.000Z",
    "newestEventAt": "2026-05-25T10:36:08.000Z",
    "gapSuspected": true,
    "error": null,
    "collectionPath": "./stats-data",
    "repo": "AdguardTeam/AdguardFilters"
  },
  {
    "timestamp": "2026-05-25T12:11:04.201Z",
    "totalEvents": 300,
    "pagesCollected": 10,
    "eventsInFile": 684,
    "rateLimitRemaining": 4989,
    "rateLimitReached": false,
    "rateLimitReset": "2026-05-25T13:10:32.000Z",
    "oldestEventAt": "2026-05-25T08:59:31.000Z",
    "newestEventAt": "2026-05-25T12:08:17.000Z",
    "gapSuspected": true,
    "error": null,
    "collectionPath": "./stats-data",
    "repo": "AdguardTeam/AdguardFilters"
  },
  {
    "timestamp": "2026-05-25T13:41:58.793Z",
    "totalEvents": 300,
    "pagesCollected": 10,
    "eventsInFile": 741,
    "rateLimitRemaining": 4989,
    "rateLimitReached": false,
    "rateLimitReset": "2026-05-25T14:41:28.000Z",
    "oldestEventAt": "2026-05-25T09:33:14.000Z",
    "newestEventAt": "2026-05-25T13:38:42.000Z",
    "gapSuspected": true,
    "error": null,
    "collectionPath": "./stats-data",
    "repo": "AdguardTeam/AdguardFilters"
  },
  {
    "timestamp": "2026-05-25T15:07:23.990Z",
    "totalEvents": 300,
    "pagesCollected": 10,
    "eventsInFile": 804,
    "rateLimitRemaining": 4989,
    "rateLimitReached": false,
    "rateLimitReset": "2026-05-25T16:06:53.000Z",
    "oldestEventAt": "2026-05-25T10:00:50.000Z",
    "newestEventAt": "2026-05-25T15:06:09.000Z",
    "gapSuspected": false,
    "error": null,
    "collectionPath": "./stats-data",
    "repo": "AdguardTeam/AdguardFilters"
  },
  {
    "timestamp": "2026-05-25T16:19:05.872Z",
    "totalEvents": 299,
    "pagesCollected": 10,
    "eventsInFile": 841,
    "rateLimitRemaining": 4989,
    "rateLimitReached": false,
    "rateLimitReset": "2026-05-25T17:18:33.000Z",
    "oldestEventAt": "2026-05-25T10:35:33.000Z",
    "newestEventAt": "2026-05-25T16:17:51.000Z",
    "gapSuspected": false,
    "error": null,
    "collectionPath": "./stats-data",
    "repo": "AdguardTeam/AdguardFilters"
  },
  {
    "timestamp": "2026-05-25T17:14:41.790Z",
    "totalEvents": 298,
    "pagesCollected": 10,
    "eventsInFile": 932,
    "rateLimitRemaining": 4978,
    "rateLimitReached": false,
    "rateLimitReset": "2026-05-25T17:18:33.000Z",
    "oldestEventAt": "2026-05-25T11:24:01.000Z",
    "newestEventAt": "2026-05-25T17:12:58.000Z",
    "gapSuspected": false,
    "error": null,
    "collectionPath": "./stats-data",
    "repo": "AdguardTeam/AdguardFilters"
  },
  {
    "timestamp": "2026-05-25T18:04:53.297Z",
    "totalEvents": 298,
    "pagesCollected": 10,
    "eventsInFile": 971,
    "rateLimitRemaining": 4989,
    "rateLimitReached": false,
    "rateLimitReset": "2026-05-25T19:04:23.000Z",
    "oldestEventAt": "2026-05-25T11:48:44.000Z",
    "newestEventAt": "2026-05-25T18:04:32.000Z",
    "gapSuspected": false,
    "error": null,
    "collectionPath": "./stats-data",
    "repo": "AdguardTeam/AdguardFilters"
  },
  {
    "timestamp": "2026-05-25T19:02:33.493Z",
    "totalEvents": 298,
    "pagesCollected": 10,
    "eventsInFile": 981,
    "rateLimitRemaining": 4978,
    "rateLimitReached": false,
    "rateLimitReset": "2026-05-25T19:04:23.000Z",
    "oldestEventAt": "2026-05-25T12:08:17.000Z",
    "newestEventAt": "2026-05-25T18:27:39.000Z",
    "gapSuspected": false,
    "error": null,
    "collectionPath": "./stats-data",
    "repo": "AdguardTeam/AdguardFilters"
  },
  {
    "timestamp": "2026-05-25T20:04:56.103Z",
    "totalEvents": 298,
    "pagesCollected": 10,
    "eventsInFile": 1031,
    "rateLimitRemaining": 4989,
    "rateLimitReached": false,
    "rateLimitReset": "2026-05-25T21:04:30.000Z",
    "oldestEventAt": "2026-05-25T13:29:51.000Z",
    "newestEventAt": "2026-05-25T20:01:12.000Z",
    "gapSuspected": false,
    "error": null,
    "collectionPath": "./stats-data",
    "repo": "AdguardTeam/AdguardFilters"
  },
  {
    "timestamp": "2026-05-25T20:53:18.659Z",
    "totalEvents": 298,
    "pagesCollected": 10,
    "eventsInFile": 1066,
    "rateLimitRemaining": 4978,
    "rateLimitReached": false,
    "rateLimitReset": "2026-05-25T21:04:30.000Z",
    "oldestEventAt": "2026-05-25T14:30:23.000Z",
    "newestEventAt": "2026-05-25T20:47:43.000Z",
    "gapSuspected": false,
    "error": null,
    "collectionPath": "./stats-data",
    "repo": "AdguardTeam/AdguardFilters"
  },
  {
    "timestamp": "2026-05-25T21:29:21.666Z",
    "totalEvents": 298,
    "pagesCollected": 10,
    "eventsInFile": 1086,
    "rateLimitRemaining": 4989,
    "rateLimitReached": false,
    "rateLimitReset": "2026-05-25T22:28:55.000Z",
    "oldestEventAt": "2026-05-25T14:48:52.000Z",
    "newestEventAt": "2026-05-25T21:16:05.000Z",
    "gapSuspected": false,
    "error": null,
    "collectionPath": "./stats-data",
    "repo": "AdguardTeam/AdguardFilters"
  },
  {
    "timestamp": "2026-05-25T21:57:17.687Z",
    "totalEvents": 298,
    "pagesCollected": 10,
    "eventsInFile": 1086,
    "rateLimitRemaining": 4978,
    "rateLimitReached": false,
    "rateLimitReset": "2026-05-25T22:28:55.000Z",
    "oldestEventAt": "2026-05-25T14:48:52.000Z",
    "newestEventAt": "2026-05-25T21:16:05.000Z",
    "gapSuspected": false,
    "error": null,
    "collectionPath": "./stats-data",
    "repo": "AdguardTeam/AdguardFilters"
  },
  {
    "timestamp": "2026-05-25T22:30:21.538Z",
    "totalEvents": 298,
    "pagesCollected": 10,
    "eventsInFile": 1087,
    "rateLimitRemaining": 4989,
    "rateLimitReached": false,
    "rateLimitReset": "2026-05-25T23:29:49.000Z",
    "oldestEventAt": "2026-05-25T14:52:08.000Z",
    "newestEventAt": "2026-05-25T22:10:25.000Z",
    "gapSuspected": false,
    "error": null,
    "collectionPath": "./stats-data",
    "repo": "AdguardTeam/AdguardFilters"
  },
  {
    "timestamp": "2026-05-25T22:55:24.984Z",
    "totalEvents": 298,
    "pagesCollected": 10,
    "eventsInFile": 1087,
    "rateLimitRemaining": 4978,
    "rateLimitReached": false,
    "rateLimitReset": "2026-05-25T23:29:49.000Z",
    "oldestEventAt": "2026-05-25T14:52:08.000Z",
    "newestEventAt": "2026-05-25T22:10:25.000Z",
    "gapSuspected": false,
    "error": null,
    "collectionPath": "./stats-data",
    "repo": "AdguardTeam/AdguardFilters"
  },
  {
    "timestamp": "2026-05-25T23:28:25.501Z",
    "totalEvents": 298,
    "pagesCollected": 10,
    "eventsInFile": 1091,
    "rateLimitRemaining": 4967,
    "rateLimitReached": false,
    "rateLimitReset": "2026-05-25T23:29:49.000Z",
    "oldestEventAt": "2026-05-25T14:53:42.000Z",
    "newestEventAt": "2026-05-25T23:14:48.000Z",
    "gapSuspected": false,
    "error": null,
    "collectionPath": "./stats-data",
    "repo": "AdguardTeam/AdguardFilters"
  },
  {
    "timestamp": "2026-05-25T23:53:52.297Z",
    "totalEvents": 298,
    "pagesCollected": 10,
    "eventsInFile": 1091,
    "rateLimitRemaining": 4989,
    "rateLimitReached": false,
    "rateLimitReset": "2026-05-26T00:53:22.000Z",
    "oldestEventAt": "2026-05-25T14:53:42.000Z",
    "newestEventAt": "2026-05-25T23:14:48.000Z",
    "gapSuspected": false,
    "error": null,
    "collectionPath": "./stats-data",
    "repo": "AdguardTeam/AdguardFilters"
  }
]