[
  {
    "timestamp": "2026-05-21T00:55:44.631Z",
    "totalEvents": 300,
    "pagesCollected": 10,
    "eventsInFile": 0,
    "rateLimitRemaining": 4989,
    "rateLimitReached": false,
    "rateLimitReset": "2026-05-21T01:55:13.000Z",
    "oldestEventAt": "2026-05-20T13:03:11.000Z",
    "newestEventAt": "2026-05-20T23:30:21.000Z",
    "gapSuspected": false,
    "error": null,
    "collectionPath": "./stats-data",
    "repo": "AdguardTeam/AdguardFilters"
  },
  {
    "timestamp": "2026-05-21T01:45:05.986Z",
    "totalEvents": 300,
    "pagesCollected": 10,
    "eventsInFile": 9,
    "rateLimitRemaining": 4978,
    "rateLimitReached": false,
    "rateLimitReset": "2026-05-21T01:55:13.000Z",
    "oldestEventAt": "2026-05-20T13:17:37.000Z",
    "newestEventAt": "2026-05-21T01:41:19.000Z",
    "gapSuspected": false,
    "error": null,
    "collectionPath": "./stats-data",
    "repo": "AdguardTeam/AdguardFilters"
  },
  {
    "timestamp": "2026-05-21T03:13:51.513Z",
    "totalEvents": 300,
    "pagesCollected": 10,
    "eventsInFile": 39,
    "rateLimitRemaining": 4989,
    "rateLimitReached": false,
    "rateLimitReset": "2026-05-21T04:13:21.000Z",
    "oldestEventAt": "2026-05-20T13:53:12.000Z",
    "newestEventAt": "2026-05-21T02:48:01.000Z",
    "gapSuspected": false,
    "error": null,
    "collectionPath": "./stats-data",
    "repo": "AdguardTeam/AdguardFilters"
  },
  {
    "timestamp": "2026-05-21T04:58:05.279Z",
    "totalEvents": 300,
    "pagesCollected": 10,
    "eventsInFile": 59,
    "rateLimitRemaining": 4989,
    "rateLimitReached": false,
    "rateLimitReset": "2026-05-21T05:57:34.000Z",
    "oldestEventAt": "2026-05-20T14:15:56.000Z",
    "newestEventAt": "2026-05-21T04:56:04.000Z",
    "gapSuspected": true,
    "error": null,
    "collectionPath": "./stats-data",
    "repo": "AdguardTeam/AdguardFilters"
  },
  {
    "timestamp": "2026-05-21T06:29:15.842Z",
    "totalEvents": 300,
    "pagesCollected": 10,
    "eventsInFile": 110,
    "rateLimitRemaining": 4989,
    "rateLimitReached": false,
    "rateLimitReset": "2026-05-21T07:28:44.000Z",
    "oldestEventAt": "2026-05-20T15:12:03.000Z",
    "newestEventAt": "2026-05-21T06:25:47.000Z",
    "gapSuspected": true,
    "error": null,
    "collectionPath": "./stats-data",
    "repo": "AdguardTeam/AdguardFilters"
  },
  {
    "timestamp": "2026-05-21T07:52:56.391Z",
    "totalEvents": 300,
    "pagesCollected": 10,
    "eventsInFile": 162,
    "rateLimitRemaining": 4989,
    "rateLimitReached": false,
    "rateLimitReset": "2026-05-21T08:52:29.000Z",
    "oldestEventAt": "2026-05-20T17:14:21.000Z",
    "newestEventAt": "2026-05-21T07:52:43.000Z",
    "gapSuspected": false,
    "error": null,
    "collectionPath": "./stats-data",
    "repo": "AdguardTeam/AdguardFilters"
  },
  {
    "timestamp": "2026-05-21T09:14:11.846Z",
    "totalEvents": 300,
    "pagesCollected": 10,
    "eventsInFile": 238,
    "rateLimitRemaining": 4989,
    "rateLimitReached": false,
    "rateLimitReset": "2026-05-21T10:13:40.000Z",
    "oldestEventAt": "2026-05-20T19:52:56.000Z",
    "newestEventAt": "2026-05-21T09:13:41.000Z",
    "gapSuspected": false,
    "error": null,
    "collectionPath": "./stats-data",
    "repo": "AdguardTeam/AdguardFilters"
  },
  {
    "timestamp": "2026-05-21T10:46:09.337Z",
    "totalEvents": 300,
    "pagesCollected": 10,
    "eventsInFile": 299,
    "rateLimitRemaining": 4989,
    "rateLimitReached": false,
    "rateLimitReset": "2026-05-21T11:45:38.000Z",
    "oldestEventAt": "2026-05-20T23:30:21.000Z",
    "newestEventAt": "2026-05-21T10:35:04.000Z",
    "gapSuspected": true,
    "error": null,
    "collectionPath": "./stats-data",
    "repo": "AdguardTeam/AdguardFilters"
  },
  {
    "timestamp": "2026-05-21T12:05:28.038Z",
    "totalEvents": 300,
    "pagesCollected": 10,
    "eventsInFile": 359,
    "rateLimitRemaining": 4989,
    "rateLimitReached": false,
    "rateLimitReset": "2026-05-21T13:04:58.000Z",
    "oldestEventAt": "2026-05-21T04:58:45.000Z",
    "newestEventAt": "2026-05-21T12:03:49.000Z",
    "gapSuspected": false,
    "error": null,
    "collectionPath": "./stats-data",
    "repo": "AdguardTeam/AdguardFilters"
  },
  {
    "timestamp": "2026-05-21T13:36:54.892Z",
    "totalEvents": 300,
    "pagesCollected": 10,
    "eventsInFile": 442,
    "rateLimitRemaining": 4989,
    "rateLimitReached": false,
    "rateLimitReset": "2026-05-21T14:36:25.000Z",
    "oldestEventAt": "2026-05-21T07:37:15.000Z",
    "newestEventAt": "2026-05-21T13:27:57.000Z",
    "gapSuspected": true,
    "error": null,
    "collectionPath": "./stats-data",
    "repo": "AdguardTeam/AdguardFilters"
  },
  {
    "timestamp": "2026-05-21T15:11:07.256Z",
    "totalEvents": 300,
    "pagesCollected": 10,
    "eventsInFile": 530,
    "rateLimitRemaining": 4989,
    "rateLimitReached": false,
    "rateLimitReset": "2026-05-21T16:10:36.000Z",
    "oldestEventAt": "2026-05-21T09:04:54.000Z",
    "newestEventAt": "2026-05-21T15:06:59.000Z",
    "gapSuspected": true,
    "error": null,
    "collectionPath": "./stats-data",
    "repo": "AdguardTeam/AdguardFilters"
  }
]