[
  {
    "timestamp": "2026-06-06T00:54:41.602Z",
    "totalEvents": 300,
    "pagesCollected": 10,
    "eventsInFile": 12,
    "rateLimitRemaining": 4989,
    "rateLimitReached": false,
    "rateLimitReset": "2026-06-06T01:54:14.000Z",
    "oldestEventAt": "2026-06-05T14:04:21.000Z",
    "newestEventAt": "2026-06-06T00:32:47.000Z",
    "gapSuspected": false,
    "error": null,
    "collectionPath": "./stats-data",
    "repo": "AdguardTeam/AdguardFilters"
  },
  {
    "timestamp": "2026-06-06T01:43:45.204Z",
    "totalEvents": 300,
    "pagesCollected": 10,
    "eventsInFile": 12,
    "rateLimitRemaining": 4978,
    "rateLimitReached": false,
    "rateLimitReset": "2026-06-06T01:54:14.000Z",
    "oldestEventAt": "2026-06-05T14:04:21.000Z",
    "newestEventAt": "2026-06-06T00:32:47.000Z",
    "gapSuspected": false,
    "error": null,
    "collectionPath": "./stats-data",
    "repo": "AdguardTeam/AdguardFilters"
  },
  {
    "timestamp": "2026-06-06T03:11:59.354Z",
    "totalEvents": 300,
    "pagesCollected": 10,
    "eventsInFile": 23,
    "rateLimitRemaining": 4989,
    "rateLimitReached": false,
    "rateLimitReset": "2026-06-06T04:11:27.000Z",
    "oldestEventAt": "2026-06-05T14:09:22.000Z",
    "newestEventAt": "2026-06-06T02:45:45.000Z",
    "gapSuspected": false,
    "error": null,
    "collectionPath": "./stats-data",
    "repo": "AdguardTeam/AdguardFilters"
  },
  {
    "timestamp": "2026-06-06T04:49:04.116Z",
    "totalEvents": 300,
    "pagesCollected": 10,
    "eventsInFile": 32,
    "rateLimitRemaining": 4989,
    "rateLimitReached": false,
    "rateLimitReset": "2026-06-06T05:48:31.000Z",
    "oldestEventAt": "2026-06-05T14:16:13.000Z",
    "newestEventAt": "2026-06-06T04:27:46.000Z",
    "gapSuspected": true,
    "error": null,
    "collectionPath": "./stats-data",
    "repo": "AdguardTeam/AdguardFilters"
  },
  {
    "timestamp": "2026-06-06T06:13:55.143Z",
    "totalEvents": 300,
    "pagesCollected": 10,
    "eventsInFile": 86,
    "rateLimitRemaining": 4989,
    "rateLimitReached": false,
    "rateLimitReset": "2026-06-06T07:13:28.000Z",
    "oldestEventAt": "2026-06-05T14:55:25.000Z",
    "newestEventAt": "2026-06-06T06:07:47.000Z",
    "gapSuspected": false,
    "error": null,
    "collectionPath": "./stats-data",
    "repo": "AdguardTeam/AdguardFilters"
  },
  {
    "timestamp": "2026-06-06T07:32:18.820Z",
    "totalEvents": 300,
    "pagesCollected": 10,
    "eventsInFile": 106,
    "rateLimitRemaining": 4989,
    "rateLimitReached": false,
    "rateLimitReset": "2026-06-06T08:31:52.000Z",
    "oldestEventAt": "2026-06-05T15:13:57.000Z",
    "newestEventAt": "2026-06-06T07:04:08.000Z",
    "gapSuspected": false,
    "error": null,
    "collectionPath": "./stats-data",
    "repo": "AdguardTeam/AdguardFilters"
  },
  {
    "timestamp": "2026-06-06T08:58:15.914Z",
    "totalEvents": 300,
    "pagesCollected": 10,
    "eventsInFile": 110,
    "rateLimitRemaining": 4989,
    "rateLimitReached": false,
    "rateLimitReset": "2026-06-06T09:57:49.000Z",
    "oldestEventAt": "2026-06-05T15:15:22.000Z",
    "newestEventAt": "2026-06-06T08:51:09.000Z",
    "gapSuspected": false,
    "error": null,
    "collectionPath": "./stats-data",
    "repo": "AdguardTeam/AdguardFilters"
  },
  {
    "timestamp": "2026-06-06T09:47:18.755Z",
    "totalEvents": 300,
    "pagesCollected": 10,
    "eventsInFile": 119,
    "rateLimitRemaining": 4978,
    "rateLimitReached": false,
    "rateLimitReset": "2026-06-06T09:57:49.000Z",
    "oldestEventAt": "2026-06-05T15:41:49.000Z",
    "newestEventAt": "2026-06-06T09:33:43.000Z",
    "gapSuspected": false,
    "error": null,
    "collectionPath": "./stats-data",
    "repo": "AdguardTeam/AdguardFilters"
  },
  {
    "timestamp": "2026-06-06T10:41:30.172Z",
    "totalEvents": 300,
    "pagesCollected": 10,
    "eventsInFile": 124,
    "rateLimitRemaining": 4989,
    "rateLimitReached": false,
    "rateLimitReset": "2026-06-06T11:41:04.000Z",
    "oldestEventAt": "2026-06-05T15:49:35.000Z",
    "newestEventAt": "2026-06-06T10:04:17.000Z",
    "gapSuspected": false,
    "error": null,
    "collectionPath": "./stats-data",
    "repo": "AdguardTeam/AdguardFilters"
  },
  {
    "timestamp": "2026-06-06T11:33:56.079Z",
    "totalEvents": 300,
    "pagesCollected": 10,
    "eventsInFile": 149,
    "rateLimitRemaining": 4978,
    "rateLimitReached": false,
    "rateLimitReset": "2026-06-06T11:41:04.000Z",
    "oldestEventAt": "2026-06-05T16:07:35.000Z",
    "newestEventAt": "2026-06-06T11:33:01.000Z",
    "gapSuspected": false,
    "error": null,
    "collectionPath": "./stats-data",
    "repo": "AdguardTeam/AdguardFilters"
  },
  {
    "timestamp": "2026-06-06T12:33:34.154Z",
    "totalEvents": 299,
    "pagesCollected": 10,
    "eventsInFile": 192,
    "rateLimitRemaining": 4989,
    "rateLimitReached": false,
    "rateLimitReset": "2026-06-06T13:33:07.000Z",
    "oldestEventAt": "2026-06-05T16:42:25.000Z",
    "newestEventAt": "2026-06-06T12:31:21.000Z",
    "gapSuspected": false,
    "error": null,
    "collectionPath": "./stats-data",
    "repo": "AdguardTeam/AdguardFilters"
  },
  {
    "timestamp": "2026-06-06T13:35:22.621Z",
    "totalEvents": 299,
    "pagesCollected": 10,
    "eventsInFile": 217,
    "rateLimitRemaining": 4989,
    "rateLimitReached": false,
    "rateLimitReset": "2026-06-06T14:34:52.000Z",
    "oldestEventAt": "2026-06-05T17:05:22.000Z",
    "newestEventAt": "2026-06-06T13:32:35.000Z",
    "gapSuspected": false,
    "error": null,
    "collectionPath": "./stats-data",
    "repo": "AdguardTeam/AdguardFilters"
  },
  {
    "timestamp": "2026-06-06T14:35:56.505Z",
    "totalEvents": 299,
    "pagesCollected": 10,
    "eventsInFile": 245,
    "rateLimitRemaining": 4989,
    "rateLimitReached": false,
    "rateLimitReset": "2026-06-06T15:35:27.000Z",
    "oldestEventAt": "2026-06-05T19:37:38.000Z",
    "newestEventAt": "2026-06-06T14:32:49.000Z",
    "gapSuspected": false,
    "error": null,
    "collectionPath": "./stats-data",
    "repo": "AdguardTeam/AdguardFilters"
  },
  {
    "timestamp": "2026-06-06T15:31:13.166Z",
    "totalEvents": 299,
    "pagesCollected": 10,
    "eventsInFile": 269,
    "rateLimitRemaining": 4978,
    "rateLimitReached": false,
    "rateLimitReset": "2026-06-06T15:35:27.000Z",
    "oldestEventAt": "2026-06-05T20:37:49.000Z",
    "newestEventAt": "2026-06-06T15:27:49.000Z",
    "gapSuspected": false,
    "error": null,
    "collectionPath": "./stats-data",
    "repo": "AdguardTeam/AdguardFilters"
  },
  {
    "timestamp": "2026-06-06T16:28:45.911Z",
    "totalEvents": 299,
    "pagesCollected": 10,
    "eventsInFile": 299,
    "rateLimitRemaining": 4989,
    "rateLimitReached": false,
    "rateLimitReset": "2026-06-06T17:28:15.000Z",
    "oldestEventAt": "2026-06-06T00:18:43.000Z",
    "newestEventAt": "2026-06-06T16:27:01.000Z",
    "gapSuspected": false,
    "error": null,
    "collectionPath": "./stats-data",
    "repo": "AdguardTeam/AdguardFilters"
  },
  {
    "timestamp": "2026-06-06T16:54:33.201Z",
    "totalEvents": 299,
    "pagesCollected": 10,
    "eventsInFile": 302,
    "rateLimitRemaining": 4978,
    "rateLimitReached": false,
    "rateLimitReset": "2026-06-06T17:28:15.000Z",
    "oldestEventAt": "2026-06-06T00:18:44.000Z",
    "newestEventAt": "2026-06-06T16:45:02.000Z",
    "gapSuspected": false,
    "error": null,
    "collectionPath": "./stats-data",
    "repo": "AdguardTeam/AdguardFilters"
  },
  {
    "timestamp": "2026-06-06T17:29:53.795Z",
    "totalEvents": 299,
    "pagesCollected": 10,
    "eventsInFile": 314,
    "rateLimitRemaining": 4989,
    "rateLimitReached": false,
    "rateLimitReset": "2026-06-06T18:29:23.000Z",
    "oldestEventAt": "2026-06-06T01:54:40.000Z",
    "newestEventAt": "2026-06-06T17:26:53.000Z",
    "gapSuspected": false,
    "error": null,
    "collectionPath": "./stats-data",
    "repo": "AdguardTeam/AdguardFilters"
  },
  {
    "timestamp": "2026-06-06T17:56:34.533Z",
    "totalEvents": 299,
    "pagesCollected": 10,
    "eventsInFile": 316,
    "rateLimitRemaining": 4978,
    "rateLimitReached": false,
    "rateLimitReset": "2026-06-06T18:29:23.000Z",
    "oldestEventAt": "2026-06-06T01:54:40.000Z",
    "newestEventAt": "2026-06-06T17:46:17.000Z",
    "gapSuspected": false,
    "error": null,
    "collectionPath": "./stats-data",
    "repo": "AdguardTeam/AdguardFilters"
  },
  {
    "timestamp": "2026-06-06T18:35:36.211Z",
    "totalEvents": 299,
    "pagesCollected": 10,
    "eventsInFile": 327,
    "rateLimitRemaining": 4989,
    "rateLimitReached": false,
    "rateLimitReset": "2026-06-06T19:35:06.000Z",
    "oldestEventAt": "2026-06-06T04:27:46.000Z",
    "newestEventAt": "2026-06-06T18:31:06.000Z",
    "gapSuspected": false,
    "error": null,
    "collectionPath": "./stats-data",
    "repo": "AdguardTeam/AdguardFilters"
  }
]