[
  {
    "timestamp": "2026-05-24T00:54:26.425Z",
    "totalEvents": 300,
    "pagesCollected": 10,
    "eventsInFile": 0,
    "rateLimitRemaining": 4989,
    "rateLimitReached": false,
    "rateLimitReset": "2026-05-24T01:54:00.000Z",
    "oldestEventAt": "2026-05-22T18:45:17.000Z",
    "newestEventAt": "2026-05-23T23:33:12.000Z",
    "gapSuspected": false,
    "error": null,
    "collectionPath": "./stats-data",
    "repo": "AdguardTeam/AdguardFilters"
  },
  {
    "timestamp": "2026-05-24T01:44:32.604Z",
    "totalEvents": 300,
    "pagesCollected": 10,
    "eventsInFile": 7,
    "rateLimitRemaining": 4978,
    "rateLimitReached": false,
    "rateLimitReset": "2026-05-24T01:54:00.000Z",
    "oldestEventAt": "2026-05-22T19:10:37.000Z",
    "newestEventAt": "2026-05-24T01:15:45.000Z",
    "gapSuspected": false,
    "error": null,
    "collectionPath": "./stats-data",
    "repo": "AdguardTeam/AdguardFilters"
  },
  {
    "timestamp": "2026-05-24T03:13:13.621Z",
    "totalEvents": 300,
    "pagesCollected": 10,
    "eventsInFile": 29,
    "rateLimitRemaining": 4989,
    "rateLimitReached": false,
    "rateLimitReset": "2026-05-24T04:12:45.000Z",
    "oldestEventAt": "2026-05-22T21:14:45.000Z",
    "newestEventAt": "2026-05-24T02:35:33.000Z",
    "gapSuspected": false,
    "error": null,
    "collectionPath": "./stats-data",
    "repo": "AdguardTeam/AdguardFilters"
  },
  {
    "timestamp": "2026-05-24T04:54:12.881Z",
    "totalEvents": 300,
    "pagesCollected": 10,
    "eventsInFile": 31,
    "rateLimitRemaining": 4989,
    "rateLimitReached": false,
    "rateLimitReset": "2026-05-24T05:53:42.000Z",
    "oldestEventAt": "2026-05-22T22:08:59.000Z",
    "newestEventAt": "2026-05-24T04:40:49.000Z",
    "gapSuspected": true,
    "error": null,
    "collectionPath": "./stats-data",
    "repo": "AdguardTeam/AdguardFilters"
  },
  {
    "timestamp": "2026-05-24T06:19:18.898Z",
    "totalEvents": 300,
    "pagesCollected": 10,
    "eventsInFile": 48,
    "rateLimitRemaining": 4989,
    "rateLimitReached": false,
    "rateLimitReset": "2026-05-24T07:18:49.000Z",
    "oldestEventAt": "2026-05-22T22:51:30.000Z",
    "newestEventAt": "2026-05-24T05:50:04.000Z",
    "gapSuspected": false,
    "error": null,
    "collectionPath": "./stats-data",
    "repo": "AdguardTeam/AdguardFilters"
  },
  {
    "timestamp": "2026-05-24T07:35:08.130Z",
    "totalEvents": 300,
    "pagesCollected": 10,
    "eventsInFile": 51,
    "rateLimitRemaining": 4989,
    "rateLimitReached": false,
    "rateLimitReset": "2026-05-24T08:34:37.000Z",
    "oldestEventAt": "2026-05-23T00:00:51.000Z",
    "newestEventAt": "2026-05-24T07:19:19.000Z",
    "gapSuspected": false,
    "error": null,
    "collectionPath": "./stats-data",
    "repo": "AdguardTeam/AdguardFilters"
  },
  {
    "timestamp": "2026-05-24T08:56:21.223Z",
    "totalEvents": 300,
    "pagesCollected": 10,
    "eventsInFile": 67,
    "rateLimitRemaining": 4989,
    "rateLimitReached": false,
    "rateLimitReset": "2026-05-24T09:55:54.000Z",
    "oldestEventAt": "2026-05-23T02:46:59.000Z",
    "newestEventAt": "2026-05-24T08:47:11.000Z",
    "gapSuspected": false,
    "error": null,
    "collectionPath": "./stats-data",
    "repo": "AdguardTeam/AdguardFilters"
  },
  {
    "timestamp": "2026-05-24T09:41:58.432Z",
    "totalEvents": 300,
    "pagesCollected": 10,
    "eventsInFile": 76,
    "rateLimitRemaining": 4978,
    "rateLimitReached": false,
    "rateLimitReset": "2026-05-24T09:55:54.000Z",
    "oldestEventAt": "2026-05-23T03:47:39.000Z",
    "newestEventAt": "2026-05-24T09:39:36.000Z",
    "gapSuspected": false,
    "error": null,
    "collectionPath": "./stats-data",
    "repo": "AdguardTeam/AdguardFilters"
  },
  {
    "timestamp": "2026-05-24T10:36:40.935Z",
    "totalEvents": 300,
    "pagesCollected": 10,
    "eventsInFile": 95,
    "rateLimitRemaining": 4989,
    "rateLimitReached": false,
    "rateLimitReset": "2026-05-24T11:36:14.000Z",
    "oldestEventAt": "2026-05-23T05:00:39.000Z",
    "newestEventAt": "2026-05-24T10:32:13.000Z",
    "gapSuspected": false,
    "error": null,
    "collectionPath": "./stats-data",
    "repo": "AdguardTeam/AdguardFilters"
  },
  {
    "timestamp": "2026-05-24T11:31:48.710Z",
    "totalEvents": 300,
    "pagesCollected": 10,
    "eventsInFile": 109,
    "rateLimitRemaining": 4978,
    "rateLimitReached": false,
    "rateLimitReset": "2026-05-24T11:36:14.000Z",
    "oldestEventAt": "2026-05-23T06:02:24.000Z",
    "newestEventAt": "2026-05-24T11:08:08.000Z",
    "gapSuspected": false,
    "error": null,
    "collectionPath": "./stats-data",
    "repo": "AdguardTeam/AdguardFilters"
  },
  {
    "timestamp": "2026-05-24T12:29:08.816Z",
    "totalEvents": 300,
    "pagesCollected": 10,
    "eventsInFile": 124,
    "rateLimitRemaining": 4989,
    "rateLimitReached": false,
    "rateLimitReset": "2026-05-24T13:28:39.000Z",
    "oldestEventAt": "2026-05-23T07:26:59.000Z",
    "newestEventAt": "2026-05-24T12:27:07.000Z",
    "gapSuspected": false,
    "error": null,
    "collectionPath": "./stats-data",
    "repo": "AdguardTeam/AdguardFilters"
  },
  {
    "timestamp": "2026-05-24T12:54:59.799Z",
    "totalEvents": 300,
    "pagesCollected": 10,
    "eventsInFile": 134,
    "rateLimitRemaining": 4978,
    "rateLimitReached": false,
    "rateLimitReset": "2026-05-24T13:28:39.000Z",
    "oldestEventAt": "2026-05-23T07:51:20.000Z",
    "newestEventAt": "2026-05-24T12:50:43.000Z",
    "gapSuspected": false,
    "error": null,
    "collectionPath": "./stats-data",
    "repo": "AdguardTeam/AdguardFilters"
  },
  {
    "timestamp": "2026-05-24T13:34:44.447Z",
    "totalEvents": 300,
    "pagesCollected": 10,
    "eventsInFile": 140,
    "rateLimitRemaining": 4989,
    "rateLimitReached": false,
    "rateLimitReset": "2026-05-24T14:34:18.000Z",
    "oldestEventAt": "2026-05-23T08:03:11.000Z",
    "newestEventAt": "2026-05-24T13:28:04.000Z",
    "gapSuspected": false,
    "error": null,
    "collectionPath": "./stats-data",
    "repo": "AdguardTeam/AdguardFilters"
  },
  {
    "timestamp": "2026-05-24T14:34:21.992Z",
    "totalEvents": 300,
    "pagesCollected": 10,
    "eventsInFile": 156,
    "rateLimitRemaining": 4995,
    "rateLimitReached": false,
    "rateLimitReset": "2026-05-24T15:34:19.000Z",
    "oldestEventAt": "2026-05-23T10:20:37.000Z",
    "newestEventAt": "2026-05-24T14:29:43.000Z",
    "gapSuspected": false,
    "error": null,
    "collectionPath": "./stats-data",
    "repo": "AdguardTeam/AdguardFilters"
  },
  {
    "timestamp": "2026-05-24T15:28:12.957Z",
    "totalEvents": 300,
    "pagesCollected": 10,
    "eventsInFile": 165,
    "rateLimitRemaining": 4984,
    "rateLimitReached": false,
    "rateLimitReset": "2026-05-24T15:34:19.000Z",
    "oldestEventAt": "2026-05-23T10:48:43.000Z",
    "newestEventAt": "2026-05-24T14:51:21.000Z",
    "gapSuspected": false,
    "error": null,
    "collectionPath": "./stats-data",
    "repo": "AdguardTeam/AdguardFilters"
  },
  {
    "timestamp": "2026-05-24T15:53:28.421Z",
    "totalEvents": 300,
    "pagesCollected": 10,
    "eventsInFile": 174,
    "rateLimitRemaining": 4989,
    "rateLimitReached": false,
    "rateLimitReset": "2026-05-24T16:52:58.000Z",
    "oldestEventAt": "2026-05-23T11:28:08.000Z",
    "newestEventAt": "2026-05-24T15:47:32.000Z",
    "gapSuspected": false,
    "error": null,
    "collectionPath": "./stats-data",
    "repo": "AdguardTeam/AdguardFilters"
  },
  {
    "timestamp": "2026-05-24T16:25:19.415Z",
    "totalEvents": 300,
    "pagesCollected": 10,
    "eventsInFile": 186,
    "rateLimitRemaining": 4978,
    "rateLimitReached": false,
    "rateLimitReset": "2026-05-24T16:52:58.000Z",
    "oldestEventAt": "2026-05-23T12:28:43.000Z",
    "newestEventAt": "2026-05-24T16:20:47.000Z",
    "gapSuspected": false,
    "error": null,
    "collectionPath": "./stats-data",
    "repo": "AdguardTeam/AdguardFilters"
  }
]