[
  {
    "totalEvents": 298,
    "pagesCollected": 10,
    "rateLimitReached": false,
    "rateLimitRemaining": 4988,
    "rateLimitReset": "2026-05-13T16:28:55.000Z",
    "timestamp": "2026-05-13T15:29:22.010Z",
    "eventsWritten": 715,
    "collectionPath": "./stats-data",
    "repo": "AdguardTeam/AdguardFilters"
  },
  {
    "timestamp": "2026-05-13T16:22:11.727Z",
    "totalEvents": 298,
    "pagesCollected": 10,
    "eventsInFile": 746,
    "rateLimitRemaining": 4976,
    "rateLimitReached": false,
    "rateLimitReset": "2026-05-13T16:28:55.000Z",
    "oldestEventAt": "2026-05-13T09:19:45.000Z",
    "newestEventAt": "2026-05-13T16:21:56.000Z",
    "gapSuspected": false,
    "error": null,
    "collectionPath": "./stats-data",
    "repo": "AdguardTeam/AdguardFilters"
  },
  {
    "timestamp": "2026-05-13T17:17:36.699Z",
    "totalEvents": 298,
    "pagesCollected": 10,
    "eventsInFile": 785,
    "rateLimitRemaining": 4988,
    "rateLimitReached": false,
    "rateLimitReset": "2026-05-13T18:17:07.000Z",
    "oldestEventAt": "2026-05-13T11:30:16.000Z",
    "newestEventAt": "2026-05-13T17:10:45.000Z",
    "gapSuspected": false,
    "error": null,
    "collectionPath": "./stats-data",
    "repo": "AdguardTeam/AdguardFilters"
  },
  {
    "timestamp": "2026-05-13T18:12:28.417Z",
    "totalEvents": 298,
    "pagesCollected": 10,
    "eventsInFile": 798,
    "rateLimitRemaining": 4976,
    "rateLimitReached": false,
    "rateLimitReset": "2026-05-13T18:17:07.000Z",
    "oldestEventAt": "2026-05-13T11:46:21.000Z",
    "newestEventAt": "2026-05-13T18:05:02.000Z",
    "gapSuspected": false,
    "error": null,
    "collectionPath": "./stats-data",
    "repo": "AdguardTeam/AdguardFilters"
  }
]